{
    "total": [
        {
            "id": "100005919548178",
            "count": 0
        },
        {
            "id": "100089476901470",
            "count": 0
        },
        {
            "id": "61556996409346",
            "count": 0
        },
        {
            "id": "100089008973608",
            "count": 0
        },
        {
            "id": "61555428134200",
            "count": 0
        },
        {
            "id": "61552477976434",
            "count": 0
        },
        {
            "id": "61559548235654",
            "count": 0
        },
        {
            "id": "61560187132936",
            "count": 0
        },
        {
            "id": "100037492783219",
            "count": 0
        },
        {
            "id": "100071003962630",
            "count": 0
        },
        {
            "id": "100084488946152",
            "count": 0
        },
        {
            "id": "61560774283761",
            "count": 0
        },
        {
            "id": "61560487154627",
            "count": 0
        },
        {
            "id": "61552176620762",
            "count": 0
        },
        {
            "id": "100084515973802",
            "count": 0
        },
        {
            "id": "100076326292406",
            "count": 0
        },
        {
            "id": "61556095743231",
            "count": 0
        },
        {
            "id": "61559895611526",
            "count": 0
        },
        {
            "id": "100089704261277",
            "count": 0
        },
        {
            "id": "61564580056415",
            "count": 0
        },
        {
            "id": "61560172074269",
            "count": 0
        },
        {
            "id": "100055236161579",
            "count": 0
        },
        {
            "id": "100088073816198",
            "count": 0
        },
        {
            "id": "100047445120815",
            "count": 0
        },
        {
            "id": "100011855520258",
            "count": 0
        },
        {
            "id": "100072653030699",
            "count": 0
        },
        {
            "id": "68126864",
            "count": 0
        },
        {
            "id": "61550962658401",
            "count": 3
        },
        {
            "id": "100094024399135",
            "count": 0
        },
        {
            "id": "61555712670336",
            "count": 0
        },
        {
            "id": "100070678868311",
            "count": 0
        },
        {
            "id": "100072301915850",
            "count": 0
        },
        {
            "id": "100093968006641",
            "count": 0
        },
        {
            "id": "100077340322638",
            "count": 0
        },
        {
            "id": "100072439105441",
            "count": 0
        },
        {
            "id": "61559339866079",
            "count": 0
        },
        {
            "id": "100068154438111",
            "count": 0
        },
        {
            "id": "61565740060446",
            "count": 0
        },
        {
            "id": "100078854755188",
            "count": 0
        },
        {
            "id": "100083700524447",
            "count": 0
        },
        {
            "id": "100085226649873",
            "count": 0
        },
        {
            "id": "100086350780713",
            "count": 0
        },
        {
            "id": "100090287744089",
            "count": 0
        },
        {
            "id": "61565691211717",
            "count": 0
        },
        {
            "id": "61567581356632",
            "count": 0
        },
        {
            "id": "61561966093395",
            "count": 0
        },
        {
            "id": "61567670670329",
            "count": 0
        },
        {
            "id": "61560445680565",
            "count": 0
        },
        {
            "id": "100073420669646",
            "count": 0
        }
    ],
    "week": [
        {
            "id": "100005919548178",
            "count": 0
        },
        {
            "id": "100089476901470",
            "count": 0
        },
        {
            "id": "61556996409346",
            "count": 0
        },
        {
            "id": "100089008973608",
            "count": 0
        },
        {
            "id": "61555428134200",
            "count": 0
        },
        {
            "id": "61552477976434",
            "count": 0
        },
        {
            "id": "61559548235654",
            "count": 0
        },
        {
            "id": "61560187132936",
            "count": 0
        },
        {
            "id": "100037492783219",
            "count": 0
        },
        {
            "id": "100071003962630",
            "count": 0
        },
        {
            "id": "100084488946152",
            "count": 0
        },
        {
            "id": "61560774283761",
            "count": 0
        },
        {
            "id": "61560487154627",
            "count": 0
        },
        {
            "id": "61552176620762",
            "count": 0
        },
        {
            "id": "100084515973802",
            "count": 0
        },
        {
            "id": "100076326292406",
            "count": 0
        },
        {
            "id": "61556095743231",
            "count": 0
        },
        {
            "id": "61559895611526",
            "count": 0
        },
        {
            "id": "100089704261277",
            "count": 0
        },
        {
            "id": "61564580056415",
            "count": 0
        },
        {
            "id": "61560172074269",
            "count": 0
        },
        {
            "id": "100055236161579",
            "count": 0
        },
        {
            "id": "100088073816198",
            "count": 0
        },
        {
            "id": "100047445120815",
            "count": 0
        },
        {
            "id": "100011855520258",
            "count": 0
        },
        {
            "id": "100072653030699",
            "count": 0
        },
        {
            "id": "68126864",
            "count": 0
        },
        {
            "id": "61550962658401",
            "count": 3
        },
        {
            "id": "100094024399135",
            "count": 0
        },
        {
            "id": "61555712670336",
            "count": 0
        },
        {
            "id": "100070678868311",
            "count": 0
        },
        {
            "id": "100072301915850",
            "count": 0
        },
        {
            "id": "100093968006641",
            "count": 0
        },
        {
            "id": "100077340322638",
            "count": 0
        },
        {
            "id": "100072439105441",
            "count": 0
        },
        {
            "id": "61559339866079",
            "count": 0
        },
        {
            "id": "100068154438111",
            "count": 0
        },
        {
            "id": "61565740060446",
            "count": 0
        },
        {
            "id": "100078854755188",
            "count": 0
        },
        {
            "id": "100083700524447",
            "count": 0
        },
        {
            "id": "100085226649873",
            "count": 0
        },
        {
            "id": "100086350780713",
            "count": 0
        },
        {
            "id": "100090287744089",
            "count": 0
        },
        {
            "id": "61565691211717",
            "count": 0
        },
        {
            "id": "61567581356632",
            "count": 0
        },
        {
            "id": "61561966093395",
            "count": 0
        },
        {
            "id": "61567670670329",
            "count": 0
        },
        {
            "id": "61560445680565",
            "count": 0
        },
        {
            "id": "100073420669646",
            "count": 0
        }
    ],
    "day": [
        {
            "id": "100005919548178",
            "count": 0,
            "name": "Người dùng facebook"
        },
        {
            "id": "100089476901470",
            "count": 0,
            "name": "Người dùng facebook"
        },
        {
            "id": "61556996409346",
            "count": 0,
            "name": "Người dùng facebook"
        },
        {
            "id": "100089008973608",
            "count": 0,
            "name": "Người dùng facebook"
        },
        {
            "id": "61555428134200",
            "count": 0,
            "name": "Người dùng facebook"
        },
        {
            "id": "61552477976434",
            "count": 0,
            "name": "Người dùng facebook"
        },
        {
            "id": "61559548235654",
            "count": 0,
            "name": "Người dùng facebook"
        },
        {
            "id": "61560187132936",
            "count": 0,
            "name": "Người dùng facebook"
        },
        {
            "id": "100037492783219",
            "count": 0,
            "name": "Người dùng facebook"
        },
        {
            "id": "100071003962630",
            "count": 0,
            "name": "Người dùng facebook"
        },
        {
            "id": "100084488946152",
            "count": 0,
            "name": "Người dùng facebook"
        },
        {
            "id": "61560774283761",
            "count": 0,
            "name": "Người dùng facebook"
        },
        {
            "id": "61560487154627",
            "count": 0,
            "name": "Người dùng facebook"
        },
        {
            "id": "61552176620762",
            "count": 0,
            "name": "Người dùng facebook"
        },
        {
            "id": "100084515973802",
            "count": 0,
            "name": "Người dùng facebook"
        },
        {
            "id": "100076326292406",
            "count": 0,
            "name": "Người dùng facebook"
        },
        {
            "id": "61556095743231",
            "count": 0,
            "name": "Người dùng facebook"
        },
        {
            "id": "61559895611526",
            "count": 0,
            "name": "Người dùng facebook"
        },
        {
            "id": "100089704261277",
            "count": 0,
            "name": "Người dùng facebook"
        },
        {
            "id": "61564580056415",
            "count": 0,
            "name": "Người dùng facebook"
        },
        {
            "id": "61560172074269",
            "count": 0,
            "name": "Người dùng facebook"
        },
        {
            "id": "100055236161579",
            "count": 0,
            "name": "Người dùng facebook"
        },
        {
            "id": "100088073816198",
            "count": 0,
            "name": "Người dùng facebook"
        },
        {
            "id": "100047445120815",
            "count": 0,
            "name": "Người dùng facebook"
        },
        {
            "id": "100011855520258",
            "count": 0,
            "name": "Người dùng facebook"
        },
        {
            "id": "100072653030699",
            "count": 0,
            "name": "Người dùng facebook"
        },
        {
            "id": "68126864",
            "count": 0,
            "name": "Người dùng facebook"
        },
        {
            "id": "61550962658401",
            "count": 0,
            "name": "Người dùng facebook"
        },
        {
            "id": "100094024399135",
            "count": 0,
            "name": "Người dùng facebook"
        },
        {
            "id": "61555712670336",
            "count": 0,
            "name": "Người dùng facebook"
        },
        {
            "id": "100070678868311",
            "count": 0,
            "name": "Người dùng facebook"
        },
        {
            "id": "100072301915850",
            "count": 0,
            "name": "Người dùng facebook"
        },
        {
            "id": "100093968006641",
            "count": 0,
            "name": "Người dùng facebook"
        },
        {
            "id": "100077340322638",
            "count": 0,
            "name": "Người dùng facebook"
        },
        {
            "id": "100072439105441",
            "count": 0,
            "name": "Người dùng facebook"
        },
        {
            "id": "61559339866079",
            "count": 0,
            "name": "Người dùng facebook"
        },
        {
            "id": "100068154438111",
            "count": 0,
            "name": "Người dùng facebook"
        },
        {
            "id": "61565740060446",
            "count": 0,
            "name": "Người dùng facebook"
        },
        {
            "id": "100078854755188",
            "count": 0,
            "name": "Người dùng facebook"
        },
        {
            "id": "100083700524447",
            "count": 0,
            "name": "Người dùng facebook"
        },
        {
            "id": "100085226649873",
            "count": 0,
            "name": "Người dùng facebook"
        },
        {
            "id": "100086350780713",
            "count": 0,
            "name": "Người dùng facebook"
        },
        {
            "id": "100090287744089",
            "count": 0,
            "name": "Người dùng facebook"
        },
        {
            "id": "61565691211717",
            "count": 0,
            "name": "Người dùng facebook"
        },
        {
            "id": "61567581356632",
            "count": 0,
            "name": "Người dùng facebook"
        },
        {
            "id": "61561966093395",
            "count": 0,
            "name": "Người dùng facebook"
        },
        {
            "id": "61567670670329",
            "count": 0,
            "name": "Người dùng facebook"
        },
        {
            "id": "61560445680565",
            "count": 0,
            "name": "Người dùng facebook"
        },
        {
            "id": "100073420669646",
            "count": 0,
            "name": "Người dùng facebook"
        }
    ],
    "time": 5,
    "last": {
        "time": 6,
        "day": [
            {
                "id": "100005919548178",
                "count": 0,
                "name": "Người dùng facebook"
            },
            {
                "id": "100089476901470",
                "count": 0,
                "name": "Người dùng facebook"
            },
            {
                "id": "61556996409346",
                "count": 0,
                "name": "Người dùng facebook"
            },
            {
                "id": "100089008973608",
                "count": 0,
                "name": "Người dùng facebook"
            },
            {
                "id": "61555428134200",
                "count": 0,
                "name": "Người dùng facebook"
            },
            {
                "id": "61552477976434",
                "count": 0,
                "name": "Người dùng facebook"
            },
            {
                "id": "61559548235654",
                "count": 0,
                "name": "Người dùng facebook"
            },
            {
                "id": "61560187132936",
                "count": 0,
                "name": "Người dùng facebook"
            },
            {
                "id": "100037492783219",
                "count": 0,
                "name": "Người dùng facebook"
            },
            {
                "id": "100071003962630",
                "count": 0,
                "name": "Người dùng facebook"
            },
            {
                "id": "100084488946152",
                "count": 0,
                "name": "Người dùng facebook"
            },
            {
                "id": "61560774283761",
                "count": 0,
                "name": "Người dùng facebook"
            },
            {
                "id": "61560487154627",
                "count": 0,
                "name": "Người dùng facebook"
            },
            {
                "id": "61552176620762",
                "count": 0,
                "name": "Người dùng facebook"
            },
            {
                "id": "100084515973802",
                "count": 0,
                "name": "Người dùng facebook"
            },
            {
                "id": "100076326292406",
                "count": 0,
                "name": "Người dùng facebook"
            },
            {
                "id": "61556095743231",
                "count": 0,
                "name": "Người dùng facebook"
            },
            {
                "id": "61559895611526",
                "count": 0,
                "name": "Người dùng facebook"
            },
            {
                "id": "100089704261277",
                "count": 0,
                "name": "Người dùng facebook"
            },
            {
                "id": "61564580056415",
                "count": 0,
                "name": "Người dùng facebook"
            },
            {
                "id": "61560172074269",
                "count": 0,
                "name": "Người dùng facebook"
            },
            {
                "id": "100055236161579",
                "count": 0,
                "name": "Người dùng facebook"
            },
            {
                "id": "100088073816198",
                "count": 0,
                "name": "Người dùng facebook"
            },
            {
                "id": "100047445120815",
                "count": 0,
                "name": "Người dùng facebook"
            },
            {
                "id": "100011855520258",
                "count": 0,
                "name": "Người dùng facebook"
            },
            {
                "id": "100072653030699",
                "count": 0,
                "name": "Người dùng facebook"
            },
            {
                "id": "68126864",
                "count": 0,
                "name": "Người dùng facebook"
            },
            {
                "id": "61550962658401",
                "count": 0,
                "name": "Người dùng facebook"
            },
            {
                "id": "100094024399135",
                "count": 0,
                "name": "Người dùng facebook"
            },
            {
                "id": "61555712670336",
                "count": 0,
                "name": "Người dùng facebook"
            },
            {
                "id": "100070678868311",
                "count": 0,
                "name": "Người dùng facebook"
            },
            {
                "id": "100072301915850",
                "count": 0,
                "name": "Người dùng facebook"
            },
            {
                "id": "100093968006641",
                "count": 0,
                "name": "Người dùng facebook"
            },
            {
                "id": "100077340322638",
                "count": 0,
                "name": "Người dùng facebook"
            },
            {
                "id": "100072439105441",
                "count": 0,
                "name": "Người dùng facebook"
            },
            {
                "id": "61559339866079",
                "count": 0,
                "name": "Người dùng facebook"
            },
            {
                "id": "100068154438111",
                "count": 0,
                "name": "Người dùng facebook"
            },
            {
                "id": "61565740060446",
                "count": 0,
                "name": "Người dùng facebook"
            },
            {
                "id": "100078854755188",
                "count": 0,
                "name": "Người dùng facebook"
            },
            {
                "id": "100083700524447",
                "count": 0,
                "name": "Người dùng facebook"
            },
            {
                "id": "100085226649873",
                "count": 0,
                "name": "Người dùng facebook"
            },
            {
                "id": "100086350780713",
                "count": 0,
                "name": "Người dùng facebook"
            },
            {
                "id": "100090287744089",
                "count": 0,
                "name": "Người dùng facebook"
            },
            {
                "id": "61565691211717",
                "count": 0,
                "name": "Người dùng facebook"
            },
            {
                "id": "61567581356632",
                "count": 0,
                "name": "Người dùng facebook"
            },
            {
                "id": "61561966093395",
                "count": 0,
                "name": "Người dùng facebook"
            },
            {
                "id": "61567670670329",
                "count": 0,
                "name": "Người dùng facebook"
            },
            {
                "id": "61560445680565",
                "count": 0,
                "name": "Người dùng facebook"
            },
            {
                "id": "100073420669646",
                "count": 0,
                "name": "Người dùng facebook"
            }
        ],
        "week": [
            {
                "id": "100005919548178",
                "count": 0
            },
            {
                "id": "100089476901470",
                "count": 0
            },
            {
                "id": "61556996409346",
                "count": 0
            },
            {
                "id": "100089008973608",
                "count": 0
            },
            {
                "id": "61555428134200",
                "count": 0
            },
            {
                "id": "61552477976434",
                "count": 0
            },
            {
                "id": "61559548235654",
                "count": 0
            },
            {
                "id": "61560187132936",
                "count": 0
            },
            {
                "id": "100037492783219",
                "count": 0
            },
            {
                "id": "100071003962630",
                "count": 0
            },
            {
                "id": "100084488946152",
                "count": 0
            },
            {
                "id": "61560774283761",
                "count": 0
            },
            {
                "id": "61560487154627",
                "count": 0
            },
            {
                "id": "61552176620762",
                "count": 0
            },
            {
                "id": "100084515973802",
                "count": 0
            },
            {
                "id": "100076326292406",
                "count": 0
            },
            {
                "id": "61556095743231",
                "count": 0
            },
            {
                "id": "61559895611526",
                "count": 0
            },
            {
                "id": "100089704261277",
                "count": 0
            },
            {
                "id": "61564580056415",
                "count": 0
            },
            {
                "id": "61560172074269",
                "count": 0
            },
            {
                "id": "100055236161579",
                "count": 0
            },
            {
                "id": "100088073816198",
                "count": 0
            },
            {
                "id": "100047445120815",
                "count": 0
            },
            {
                "id": "100011855520258",
                "count": 0
            },
            {
                "id": "100072653030699",
                "count": 0
            },
            {
                "id": "68126864",
                "count": 0
            },
            {
                "id": "61550962658401",
                "count": 0
            },
            {
                "id": "100094024399135",
                "count": 0
            },
            {
                "id": "61555712670336",
                "count": 0
            },
            {
                "id": "100070678868311",
                "count": 0
            },
            {
                "id": "100072301915850",
                "count": 0
            },
            {
                "id": "100093968006641",
                "count": 0
            },
            {
                "id": "100077340322638",
                "count": 0
            },
            {
                "id": "100072439105441",
                "count": 0
            },
            {
                "id": "61559339866079",
                "count": 0
            },
            {
                "id": "100068154438111",
                "count": 0
            },
            {
                "id": "61565740060446",
                "count": 0
            },
            {
                "id": "100078854755188",
                "count": 0
            },
            {
                "id": "100083700524447",
                "count": 0
            },
            {
                "id": "100085226649873",
                "count": 0
            },
            {
                "id": "100086350780713",
                "count": 0
            },
            {
                "id": "100090287744089",
                "count": 0
            },
            {
                "id": "61565691211717",
                "count": 0
            },
            {
                "id": "61567581356632",
                "count": 0
            },
            {
                "id": "61561966093395",
                "count": 0
            },
            {
                "id": "61567670670329",
                "count": 0
            },
            {
                "id": "61560445680565",
                "count": 0
            },
            {
                "id": "100073420669646",
                "count": 0
            }
        ]
    }
}